mc3479.py
circuitpython_mc3479-0.2.1.dist-info/LICENSE
circuitpython_mc3479-0.2.1.dist-info/METADATA
circuitpython_mc3479-0.2.1.dist-info/WHEEL
circuitpython_mc3479-0.2.1.dist-info/top_level.txt
circuitpython_mc3479-0.2.1.dist-info/RECORD
