Metadata-Version: 2.1
Name: circuitpython-mc3479
Version: 0.2.1
Summary: MC3479 Accelerometer Driver
Author-email: JDM <jdm@mozmail.com>
License: MIT
Project-URL: Homepage, https://github.com/jposada202020/CircuitPython_MC3479
Keywords: adafruit,blinka,circuitpython,micropython,mc3479,accelerometer,driver,acceleration,CircuitPython,MC3479,sensor
Classifier: Intended Audience :: Developers
Classifier: Topic :: Software Development :: Libraries
Classifier: Topic :: Software Development :: Embedded Systems
Classifier: Topic :: System :: Hardware
Classifier: License :: OSI Approved :: MIT License
Classifier: Programming Language :: Python :: 3
License-File: LICENSE
Requires-Dist: Adafruit-Blinka
Requires-Dist: adafruit-circuitpython-busdevice
Requires-Dist: adafruit-circuitpython-register
Provides-Extra: optional
